{
  "_class": "shapeGroup",
  "clippingMaskMode": 0,
  "do_objectID": "A1CFEC46-A8DE-4DBF-83CC-D1EAEDB2BC0B",
  "exportOptions": {
    "_class": "exportOptions",
    "exportFormats": [
    ],
    "includedLayerIds": [
    ],
    "layerOptions": 0,
    "shouldTrim": false
  },
  "frame": {
    "_class": "rect",
    "constrainProportions": false,
    "height": 1,
    "width": 16,
    "x": 9,
    "y": 2
  },
  "hasClickThrough": false,
  "hasClippingMask": false,
  "isFlippedHorizontal": false,
  "isFlippedVertical": false,
  "isLocked": false,
  "isVisible": true,
  "layerListExpandedType": 1,
  "layers": [
    {
      "class": "rectangle",
      "id": "B14B7893-5781-47E1-916B-12E27EC37F39"
    }
  ],
  "name": "line",
  "nameIsFixed": false,
  "resizingConstraint": 63,
  "resizingType": 0,
  "rotation": 0,
  "shouldBreakMaskChain": false,
  "style": {
    "sharedObjectID": "14D2B060-924B-42A0-AA9B-43C69FE21498"
  },
  "windingRule": 1
}